UtilForWhatching/LookInJupyter.py
UtilForWhatching/__init__.py
look_with_jupyter-0.1.5.dist-info/METADATA
look_with_jupyter-0.1.5.dist-info/WHEEL
look_with_jupyter-0.1.5.dist-info/RECORD
