Metadata-Version: 2.4
Name: look-with-jupyter
Version: 0.1.5
Summary: Модуль для просмотра таблиц polars или pandas с помощью виджетов Jupyter
Project-URL: Homepage, https://github.com/yourusername/look-with-jupyter
Project-URL: Documentation, https://github.com/yourusername/look-with-jupyter
Project-URL: Repository, https://github.com/yourusername/look-with-jupyter.git
Project-URL: Issues, https://github.com/yourusername/look-with-jupyter/issues
Author-email: PKALab <kpalab@pkotlyarov.ru>
License: MIT
Keywords: dataframe,jupyter,pandas,polars,widgets
Classifier: Development Status :: 3 - Alpha
Classifier: Intended Audience :: Developers
Classifier: License :: OSI Approved :: MIT License
Classifier: Programming Language :: Python :: 3
Classifier: Programming Language :: Python :: 3.11
Classifier: Programming Language :: Python :: 3.12
Requires-Python: >=3.11
Provides-Extra: dev
Requires-Dist: black>=23.0.0; extra == 'dev'
Requires-Dist: mypy>=1.0.0; extra == 'dev'
Requires-Dist: pytest-cov>=4.0.0; extra == 'dev'
Requires-Dist: pytest>=7.0.0; extra == 'dev'
Requires-Dist: ruff>=0.1.0; extra == 'dev'
Provides-Extra: jupyter
Requires-Dist: ipython>=7.0.0; extra == 'jupyter'
Requires-Dist: ipywidgets>=8.0.0; extra == 'jupyter'
Requires-Dist: pandas>=1.0.0; extra == 'jupyter'
Requires-Dist: polars>=0.20.0; extra == 'jupyter'
Provides-Extra: test
Requires-Dist: ipython>=7.0.0; extra == 'test'
Requires-Dist: ipywidgets>=8.0.0; extra == 'test'
Requires-Dist: pandas>=1.0.0; extra == 'test'
Requires-Dist: polars>=0.20.0; extra == 'test'
Requires-Dist: pytest-cov>=4.0.0; extra == 'test'
Requires-Dist: pytest>=7.0.0; extra == 'test'
